{
    "amiibo": [
        {
            "id": 1,
            "head": "00000000",
            "tail": "00000002",
            "name": {
                "en": "Minda & Wolf link",
                "jp": "ミンダとワルフリンク",
                "zh": "林克狼"
            }
        },
        {
            "id": 2,
            "head": "00000000",
            "tail": "00340102",
            "name": {
                "en": "Minda & Wolf link",
                "jp": "ミンダとワルフリンク",
                "zh": "林克狼"
            }
        }
    ],
    "game": [
        {
            "id": 1,
            "name": {
                "en": "Mario Kart 8",
                "jp": "マリオカート8",
                "zh": "马里奥赛车8"
            },
            "links": [
                {
                    "amiibo_id": 1,
                    "usage": {
                        "en": "Mario Kart 8",
                        "jp": "マリオカート8",
                        "zh": "马里奥赛车8"
                    }
                },
                {
                    "amiibo_id": 1,
                    "usage": {
                        "en": "Mario Kart 8",
                        "jp": "マリオカート8",
                        "zh": "马里奥赛车8"
                    }
                }
            ]
        },
        {
            "id": 2,
            "name": {
                "en": "Mario Kart 8 Deluxe",
                "jp": "マリオカート8デラックス",
                "zh": "马里奥赛车8 豪华版"
            },
            "links": [
                {
                    "amiibo_id": 1,
                    "usage": {
                        "en": "Mario Kart 8",
                        "jp": "マリオカート8",
                        "zh": "马里奥赛车8"
                    }
                },
                {
                    "amiibo_id": 1,
                    "usage": {
                        "en": "Mario Kart 8",
                        "jp": "マリオカート8",
                        "zh": "马里奥赛车8"
                    }
                }
            ]
        },
        {
            "id": 3,
            "name": {
                "en": "Animal Crossing",
                "jp": "マリオカート8デラックス",
                "zh": "动物森友会"
            },
            "links": [],
            "games": [
                {
                    "id": 4,
                    "name": {
                        "en": "100 Animal Series1",
                        "jp": "ニューハイジングス",
                        "zh": "动森100村民 1"
                    },
                    "link": [
                        {
                            "amiibo_id": 1,
                            "usage": {
                                "en": "Mario Kart 8",
                                "jp": "マリオカート8",
                                "zh": "马里奥赛车8"
                            }
                        }
                    ]
                }
            ]
        }
    ]
}